pyliara/__init__.py
pyliara/liara.py
pyliara/mmd.py
pyliara-1.4.3.dist-info/LICENCE
pyliara-1.4.3.dist-info/METADATA
pyliara-1.4.3.dist-info/WHEEL
pyliara-1.4.3.dist-info/top_level.txt
pyliara-1.4.3.dist-info/RECORD
