Metadata-Version: 2.1
Name: pyliara
Version: 1.4.3
Summary: This is an unofficial library for Liara Host
Home-page: https://rubika.ir/Mohamadreza_firouzi
Author: MohammadRezaFirouzi
Author-email: mrfirouziii@gmail.com
License: UNKNOWN
Platform: UNKNOWN
Classifier: Programming Language :: Python :: 3
Classifier: License :: OSI Approved :: MIT License
Classifier: Topic :: Internet
Requires-Python: ~=3.7
License-File: LICENCE
Requires-Dist: requests
